search_proto/search_pb2.py
search_proto/search_pb2_grpc.py
search_proto-0.1.0.dist-info/LICENSE
search_proto-0.1.0.dist-info/METADATA
search_proto-0.1.0.dist-info/WHEEL
search_proto-0.1.0.dist-info/top_level.txt
search_proto-0.1.0.dist-info/RECORD
