Metadata-Version: 2.1
Name: search-proto
Version: 0.1.0
Summary: This package contains Standard Search Proto messages and gRPC stubs definitions
Home-page: https://www.zooper.co
Author: Zooper
Author-email: hi@zooper.com
License: Apache License, Version 2.0
Keywords: search proto
Platform: UNKNOWN
Classifier: Development Status :: 3 - Alpha
Classifier: Intended Audience :: Developers
Classifier: Natural Language :: English
Classifier: Operating System :: POSIX :: Linux
Classifier: Programming Language :: Python :: 3.6
Classifier: License :: OSI Approved :: Apache Software License
Requires-Dist: grpcio (>=1.22.0)
Requires-Dist: grpcio-tools (>=1.23.0)
Requires-Dist: protobuf (>=3.9.0)
